canonicaljson/__init__.py
canonicaljson/canonicaljson.cpython-39-arm-linux-gnueabihf.so
canonicaljson_rs-0.9.3.dist-info/METADATA
canonicaljson_rs-0.9.3.dist-info/WHEEL
canonicaljson_rs-0.9.3.dist-info/RECORD
