Metadata-Version: 2.4
Name: canonicaljson-rs
Version: 0.9.3
Summary: Python bindings for canonical_json
Author: Mathieu Leplatre <mathieu@mozilla.com>
Author-email: Mathieu Leplatre <mathieu@mozilla.com>
License: Mozilla Public License 2.0
Project-URL: Source Code, https://github.com/leplatrem/python-canonicaljson-rs/
